<?xml version="1.0" encoding="UTF-8"?>
<MSG>
    <BODY>
        <DO-DATA>
            <USER_DATA_ENTITLEMENT ALLOW_SHORT_SELL_APPROVAL_IND="N" ALL_AE_4_ORDER_APPR_IND="N" ALL_AE_4_ORDER_INPUT_IND="N" ALL_BROKER_EXCH_IND="N" ALL_EXCH_IND="N" APPR_OWN_ORDER_IND="N" CLIENT_OID="2017582" DEFAULT_OPER_UNIT_OID="240001" LAST_MOD_TIMESTAMP="2014/04/16 18:02:20" LAST_MOD_USER="PPAK01" MANAGE_AE_UNDER_ALL_OU_IND="N" OPER_UNIT_OID="240001" STATUS="A" SYNCSTR="2014/04/16 18:02:20" USER_OID="6000100303" USER_ROLE_OID="430006" VERSION="1">
                <USER_ACCESSIBLE_AE AE_OID="2000348" LAST_MOD_TIMESTAMP="2015/11/25 11:16:13" LAST_MOD_USER="DEMO01" STATUS="A" SYNCSTR="2015/11/25 11:16:13" USER_ACCESSIBLE_AE_OID="1" USER_OID="6000100303" VERSION="1"/>
            </USER_DATA_ENTITLEMENT>
        </DO-DATA>
    </BODY>
    <HEADER CL_ERR_CODE="" CL_ERR_PARA="" CL_RESULT="CL_SUCCESS"/>
</MSG>
